<widget class="QDialog" name="IDD_STRING_DLG">
	<property name="geometry">
		<rect>
			<x>0</x>
			<y>0</y>
			<width>151</width>
			<height>52</height>
		</rect>
	</property>
	<property name="windowTitle">
		<string />
	</property>
	<widget class="QLabel" name="IDC_STRING_STATIC">
		<property name="geometry">
			<rect>
				<x>6</x>
				<y>4</y>
				<width>42</width>
				<height>8</height>
			</rect>
		</property>
		<property name="text">
			<string>STATIC :</string>
		</property>
	</widget>
	<widget class="QLineEdit" name="IDC_STRING_EDIT">
		<property name="geometry">
			<rect>
				<x>49</x>
				<y>2</y>
				<width>88</width>
				<height>14</height>
			</rect>
		</property>
	</widget>
	<widget class="QPushButton" name="IDOK">
		<property name="geometry">
			<rect>
				<x>20</x>
				<y>26</y>
				<width>50</width>
				<height>14</height>
			</rect>
		</property>
		<property name="text">
			<string>OK</string>
		</property>
	</widget>
	<widget class="QPushButton" name="IDCANCEL">
		<property name="geometry">
			<rect>
				<x>87</x>
				<y>26</y>
				<width>50</width>
				<height>14</height>
			</rect>
		</property>
		<property name="text">
			<string>Cancel</string>
		</property>
	</widget>
</widget>
